README.md
setup.py
SungrowClient/SungrowClient.py
SungrowClient/__init__.py
SungrowClient/version.py
SungrowClient.egg-info/PKG-INFO
SungrowClient.egg-info/SOURCES.txt
SungrowClient.egg-info/dependency_links.txt
SungrowClient.egg-info/requires.txt
SungrowClient.egg-info/top_level.txt