Metadata-Version: 2.1
Name: SungrowClient
Version: 0.1.0
Summary: A wrapper for talking to Sungrow Inverters via Modbus and HTTP API
Home-page: https://github.com/bohdan-s/SungrowClient
Author: Bohdan Flower
Author-email: github@bohdan.net
License: UNKNOWN
Platform: UNKNOWN
Classifier: Programming Language :: Python :: 3
Classifier: License :: OSI Approved :: GNU General Public License v3 (GPLv3)
Classifier: Operating System :: OS Independent
Requires-Python: >=3.5.0
